funksnake/__init__.py
funksnake/__main__.py
funksnake/base.py
funksnake/enums.py
funksnake/accessors/__init__.py
funksnake/accessors/api.py
funksnake/accessors/base.py
funksnake/aio/__init__.py
funksnake/aio/accessors/__init__.py
funksnake/aio/accessors/api.py
funksnake/aio/accessors/base.py
funksnake/sio/__init__.py
funksnake/sio/accessors/__init__.py
funksnake/sio/accessors/api.py
funksnake/sio/accessors/base.py
funksnake-0.0.4.dist-info/LICENSE
funksnake-0.0.4.dist-info/METADATA
funksnake-0.0.4.dist-info/WHEEL
funksnake-0.0.4.dist-info/top_level.txt
funksnake-0.0.4.dist-info/RECORD
