Metadata-Version: 2.1
Name: funksnake
Version: 0.0.4
Summary: Python wrapper for funkwhale api
Home-page: https://github.com/gammelalf/funksnake
Author: Wolfgang Fischer
Author-email: 31348226+gammelalf@users.noreply.github.com
License: UNKNOWN
Platform: UNKNOWN
Classifier: Programming Language :: Python :: 3
Classifier: License :: OSI Approved :: GNU General Public License v2 or later (GPLv2+)
Classifier: Operating System :: OS Independent
Requires-Python: >=3.6
License-File: LICENSE
Requires-Dist: aiohttp[speedups] (~=3.7.3)
Requires-Dist: setuptools (~=53.0.0)
Requires-Dist: requests (~=2.25.1)
